tlpui/__init__.py
tlpui/__main__.py
tlpui/backend.py
tlpui/cmdhelper.py
tlpui/config.py
tlpui/configschema/1_3.yaml
tlpui/configschema/1_4.yaml
tlpui/configschema/1_5.yaml
tlpui/configschema/1_6.yaml
tlpui/configschema/1_7.yaml
tlpui/configschema/1_8.yaml
tlpui/configschema/1_9.yaml
tlpui/configui.py
tlpui/constants.py
tlpui/css.py
tlpui/defaults/tlp-1_3.conf
tlpui/defaults/tlp-1_4.conf
tlpui/defaults/tlp-1_5.conf
tlpui/defaults/tlp-1_6.conf
tlpui/defaults/tlp-1_7.conf
tlpui/defaults/tlp-1_8.conf
tlpui/defaults/tlp-1_9.conf
tlpui/errorui.py
tlpui/file.py
tlpui/filehelper.py
tlpui/icons/ICON-AUTHORS
tlpui/icons/OnAC.svg
tlpui/icons/OnBAT.svg
tlpui/icons/dropin.svg
tlpui/icons/flags/de_DE.png
tlpui/icons/flags/en_EN.png
tlpui/icons/flags/es_ES.png
tlpui/icons/flags/fr_FR.png
tlpui/icons/flags/hu_HU.png
tlpui/icons/flags/id_ID.png
tlpui/icons/flags/it_IT.png
tlpui/icons/flags/pt_BR.png
tlpui/icons/flags/ru_RU.png
tlpui/icons/flags/tr_TR.png
tlpui/icons/flags/zh.png
tlpui/icons/flags/zh_CN.png
tlpui/icons/flags/zh_TW.png
tlpui/icons/themeable/hicolor/128x128/apps/tlpui.png
tlpui/icons/themeable/hicolor/16x16/apps/tlpui.png
tlpui/icons/themeable/hicolor/256x256/apps/tlpui.png
tlpui/icons/themeable/hicolor/32x32/apps/tlpui.png
tlpui/icons/themeable/hicolor/48x48/apps/tlpui.png
tlpui/icons/themeable/hicolor/64x64/apps/tlpui.png
tlpui/icons/themeable/hicolor/96x96/apps/tlpui.png
tlpui/icons/themeable/hicolor/scalable/actions/dialog-information-symbolic.svg
tlpui/icons/themeable/hicolor/scalable/actions/document-save-symbolic.svg
tlpui/icons/themeable/hicolor/scalable/actions/edit-symbolic.svg
tlpui/icons/themeable/hicolor/scalable/actions/format-indent-more-symbolic.svg
tlpui/icons/themeable/hicolor/scalable/actions/list-add-symbolic.svg
tlpui/icons/themeable/hicolor/scalable/actions/tlpui-Audio-symbolic.svg
tlpui/icons/themeable/hicolor/scalable/actions/tlpui-Disks-symbolic.svg
tlpui/icons/themeable/hicolor/scalable/actions/tlpui-Dock-symbolic.svg
tlp_ui-1.9.0.dist-info/METADATA
tlp_ui-1.9.0.dist-info/WHEEL
tlp_ui-1.9.0.dist-info/entry_points.txt
tlp_ui-1.9.0.dist-info/licenses/COPYING.md
tlp_ui-1.9.0.dist-info/licenses/LICENSE.md
tlp_ui-1.9.0.dist-info/RECORD
