Metadata-Version: 2.4
Name: tlp-ui
Version: 1.9.0
Summary: GTK UI for tlp
License: GPL-2.0-or-later
License-File: COPYING.md
License-File: LICENSE.md
Keywords: battery,power,config
Author: Daniel Christophis
Author-email: code@devmind.org
Requires-Python: >=3.10.0,<4.0.0
Classifier: License :: OSI Approved :: GNU General Public License v2 or later (GPLv2+)
Classifier: Programming Language :: Python :: 3
Classifier: Programming Language :: Python :: 3.10
Classifier: Programming Language :: Python :: 3.11
Classifier: Programming Language :: Python :: 3.12
Classifier: Programming Language :: Python :: 3.13
Classifier: Programming Language :: Python :: 3.14
Classifier: Topic :: Utilities
Requires-Dist: pygobject (>=3.46.0,<4.0.0)
Requires-Dist: pyyaml (>=6.0.1,<7.0.0)
Project-URL: Documentation, https://github.com/d4nj1/TLPUI/docs
Project-URL: Homepage, https://github.com/d4nj1/TLPUI
Project-URL: Repository, https://github.com/d4nj1/TLPUI
